Users/User/AppData/Local/Temp/build-env-8toyjbo3/src/autoTestScheme/allure/bin/allure
Users/User/AppData/Local/Temp/build-env-8toyjbo3/src/autoTestScheme/allure/bin/allure.bat
Users/User/AppData/Local/Temp/build-env-8toyjbo3/src/autoTestScheme/allure/config/allure-cucumber.yml
Users/User/AppData/Local/Temp/build-env-8toyjbo3/src/autoTestScheme/allure/config/allure-junit.yml
Users/User/AppData/Local/Temp/build-env-8toyjbo3/src/autoTestScheme/allure/config/allure.yml
Users/User/AppData/Local/Temp/build-env-8toyjbo3/src/autoTestScheme/allure/lib/allure-commandline-2.15.0.jar
Users/User/AppData/Local/Temp/build-env-8toyjbo3/src/autoTestScheme/allure/lib/allure-generator-2.15.0.jar
Users/User/AppData/Local/Temp/build-env-8toyjbo3/src/autoTestScheme/allure/lib/allure-model-2.15.0.jar
Users/User/AppData/Local/Temp/build-env-8toyjbo3/src/autoTestScheme/allure/lib/allure-plugin-api-2.15.0.jar
Users/User/AppData/Local/Temp/build-env-8toyjbo3/src/autoTestScheme/allure/lib/allure1-model-1.0.jar
Users/User/AppData/Local/Temp/build-env-8toyjbo3/src/autoTestScheme/allure/lib/annotations-15.0.jar
Users/User/AppData/Local/Temp/build-env-8toyjbo3/src/autoTestScheme/allure/lib/commons-beanutils-1.9.4.jar
Users/User/AppData/Local/Temp/build-env-8toyjbo3/src/autoTestScheme/allure/lib/commons-codec-1.11.jar
Users/User/AppData/Local/Temp/build-env-8toyjbo3/src/autoTestScheme/allure/lib/commons-collections-3.2.2.jar
Users/User/AppData/Local/Temp/build-env-8toyjbo3/src/autoTestScheme/allure/lib/commons-collections4-4.2.jar
Users/User/AppData/Local/Temp/build-env-8toyjbo3/src/autoTestScheme/allure/lib/commons-io-2.11.0.jar
Users/User/AppData/Local/Temp/build-env-8toyjbo3/src/autoTestScheme/allure/lib/commons-lang3-3.12.0.jar
Users/User/AppData/Local/Temp/build-env-8toyjbo3/src/autoTestScheme/allure/lib/commons-logging-1.2.jar
Users/User/AppData/Local/Temp/build-env-8toyjbo3/src/autoTestScheme/allure/lib/commons-text-1.3.jar
autoTestScheme-0.2.0.37.dist-info/METADATA
autoTestScheme-0.2.0.37.dist-info/WHEEL
autoTestScheme-0.2.0.37.dist-info/entry_points.txt
autoTestScheme-0.2.0.37.dist-info/top_level.txt
autoTestScheme-0.2.0.37.dist-info/RECORD
