Metadata-Version: 2.1
Name: autoTestScheme
Version: 0.2.0.37
Summary: auto test scheme
Home-page: https://gitee.com/xiongrun/auto-test-scheme
Author: wuxin
Author-email: xr18668178362@163.com
Project-URL: Bug Tracker, https://gitee.com/xiongrun/auto-test-scheme/issues
Requires-Dist: locust
Requires-Dist: redis-py-cluster
Requires-Dist: pluggy (==0.13.1)
Requires-Dist: loguru
Requires-Dist: dingtalkchatbot
Requires-Dist: allure-pytest
Requires-Dist: pytest-ordering
Requires-Dist: pymysql
Requires-Dist: json-tools
Requires-Dist: pytest (~=6.2.5)
Requires-Dist: pako (~=0.3.1)
Requires-Dist: websocket-client
Requires-Dist: Faker
Requires-Dist: pycryptodome
Requires-Dist: dynaconf
Requires-Dist: selenium
Requires-Dist: webdriver-manager
